reduce_binary/__init__.py
reduce_binary/executable.py
reduce_binary/executable.pyi
reduce_binary/helpers.py
reduce_binary/reduce_wwPDB_het_dict.txt
reduce_binary/bin/reduce
reduce_binary-4.15.0.dist-info/licenses/LICENSE
reduce_binary-4.15.0.dist-info/METADATA
reduce_binary-4.15.0.dist-info/WHEEL
reduce_binary-4.15.0.dist-info/top_level.txt
reduce_binary-4.15.0.dist-info/RECORD
