Metadata-Version: 2.4
Name: reduce-binary
Version: 4.15.0
Summary: Install reduce with pip
Author: Kiyoon Kim
License:                                  Apache License
Project-URL: Homepage, https://github.com/deargen/py-reduce-binary
Keywords: biology
Classifier: Programming Language :: Python :: Implementation :: CPython
Classifier: Programming Language :: Python
Classifier: Programming Language :: Python :: 3
Classifier: Programming Language :: Python :: 3.10
Classifier: Programming Language :: Python :: 3.11
Classifier: Programming Language :: Python :: 3.12
Classifier: Programming Language :: Python :: 3.13
Classifier: License :: OSI Approved :: Apache Software License
Requires-Python: <4,>=3.10
License-File: LICENSE
Dynamic: license-file
